README.md
setup.py
cog_nba/__init__.py
cog_nba/database.py
cog_nba/manage.py
cog_nba/nba.py
cog_nba/settings.py
cog_nba.egg-info/PKG-INFO
cog_nba.egg-info/SOURCES.txt
cog_nba.egg-info/dependency_links.txt
cog_nba.egg-info/requires.txt
cog_nba.egg-info/top_level.txt