Metadata-Version: 2.1
Name: cog-nba
Version: 0.0.8
Summary: A wrapper over the stats.nba.com API which builds in caching of GET queries.
Home-page: https://andryo.co
Author: Andryo Marzuki
Author-email: stabbish@gmail.com
License: UNKNOWN
Platform: UNKNOWN
Classifier: Programming Language :: Python :: 3
Classifier: License :: OSI Approved :: MIT License
Classifier: Operating System :: OS Independent
